ledgerwallet/__init__.py
ledgerwallet/__version__.py
ledgerwallet/client.py
ledgerwallet/hsmscript.py
ledgerwallet/hsmserver.py
ledgerwallet/ledgerctl.py
ledgerwallet/ledgerserver.py
ledgerwallet/manifest.py
ledgerwallet/manifest_json.py
ledgerwallet/manifest_toml.py
ledgerwallet/params.py
ledgerwallet/simpleserver.py
ledgerwallet/utils.py
ledgerwallet/crypto/__init__.py
ledgerwallet/crypto/ecc.py
ledgerwallet/crypto/scp.py
ledgerwallet/proto/LedgerHSMServer.proto
ledgerwallet/proto/LedgerHSMServer_pb2.py
ledgerwallet/proto/LedgerHSMServer_pb2.pyi
ledgerwallet/proto/__init__.py
ledgerwallet/proto/listApps.proto
ledgerwallet/proto/listApps_pb2.py
ledgerwallet/proto/listApps_pb2.pyi
ledgerwallet/transport/__init__.py
ledgerwallet/transport/device.py
ledgerwallet/transport/file.py
ledgerwallet/transport/hid.py
ledgerwallet/transport/tcp.py
ledgerwallet-0.8.1.dist-info/licenses/LICENSE
ledgerwallet-0.8.1.dist-info/METADATA
ledgerwallet-0.8.1.dist-info/WHEEL
ledgerwallet-0.8.1.dist-info/entry_points.txt
ledgerwallet-0.8.1.dist-info/top_level.txt
ledgerwallet-0.8.1.dist-info/RECORD
