Metadata-Version: 2.4
Name: ledgerwallet
Version: 0.8.1
Summary: Library to communicate between the Ledger devices (Nano S/S+/X, Stax, Flex, Apex P and Apex M) and Speculos
Author-email: Ledger <hello@ledger.fr>
License-Expression: MIT
Project-URL: Home, https://github.com/LedgerHQ/ledgerctl
Classifier: Programming Language :: Python :: 3
Classifier: Programming Language :: Python :: 3.9
Classifier: Programming Language :: Python :: 3.10
Classifier: Programming Language :: Python :: 3.11
Classifier: Programming Language :: Python :: 3.12
Classifier: Programming Language :: Python :: 3.13
Classifier: Operating System :: POSIX :: Linux
Classifier: Operating System :: Microsoft :: Windows
Classifier: Operating System :: MacOS :: MacOS X
Requires-Python: >=3.9
License-File: LICENSE
Requires-Dist: click>=8.0
Requires-Dist: construct>=2.10
Requires-Dist: cryptography>=2.5
Requires-Dist: ecdsa
Requires-Dist: hidapi
Requires-Dist: intelhex
Requires-Dist: Pillow
Requires-Dist: protobuf<6,>=5.28
Requires-Dist: requests
Requires-Dist: tabulate
Requires-Dist: toml
Dynamic: license-file
